bench_runner/__init__.py
bench_runner/__main__.py
bench_runner/bases.py
bench_runner/benchmark_definitions.py
bench_runner/config.py
bench_runner/flags.py
bench_runner/gh.py
bench_runner/git.py
bench_runner/hpt.py
bench_runner/plot.py
bench_runner/result.py
bench_runner/runners.py
bench_runner/table.py
bench_runner/util.py
bench_runner/scripts/__init__.py
bench_runner/scripts/backfill.py
bench_runner/scripts/bisect.py
bench_runner/scripts/compare.py
bench_runner/scripts/find_failures.py
bench_runner/scripts/generate_results.py
bench_runner/scripts/get_merge_base.py
bench_runner/scripts/install.py
bench_runner/scripts/notify.py
bench_runner/scripts/profiling_plot.py
bench_runner/scripts/purge.py
bench_runner/scripts/remove_benchmark.py
bench_runner/scripts/run_benchmarks.py
bench_runner/scripts/synthesize_loops_file.py
bench_runner/scripts/workflow.py
bench_runner/templates/README.md
bench_runner/templates/RESULTS.md
bench_runner/templates/_benchmark.src.yml
bench_runner/templates/_find_failures.src.yml
bench_runner/templates/_generate.src.yml
bench_runner/templates/_notify.src.yml
bench_runner/templates/_publish.src.yml
bench_runner/templates/_pystats.src.yml
bench_runner/templates/_weekly.src.yml
bench_runner/templates/bench_runner.toml
bench_runner/templates/benchmark.src.yml
bench_runner/templates/benchmarks.manifest
bench_runner/templates/ci.src.yml
bench_runner/templates/workflow_bootstrap.src.py
bench_runner-2.0.8.dist-info/licenses/LICENSE
bench_runner-2.0.8.dist-info/METADATA
bench_runner-2.0.8.dist-info/WHEEL
bench_runner-2.0.8.dist-info/top_level.txt
bench_runner-2.0.8.dist-info/RECORD
