Metadata-Version: 2.4
Name: bench_runner
Version: 2.0.8
Summary: Faster CPython's benchmarking runner utilities
Author-email: Michael Droettboom <mdroettboom@microsoft.com>
License: BSD-3-Clause
Classifier: Programming Language :: Python :: 3
Requires-Python: >=3.11
License-File: LICENSE
Requires-Dist: matplotlib==3.10.3
Requires-Dist: pyperf==2.9.0
Requires-Dist: rich==14.0.0
Requires-Dist: rich-argparse==1.7.1
Requires-Dist: ruamel.yaml==0.18.14
Requires-Dist: scour==0.38.2
Requires-Dist: wheel
Provides-Extra: test
Requires-Dist: black==25.1.0; extra == "test"
Requires-Dist: filelock==3.18.0; extra == "test"
Requires-Dist: flake8==7.3.0; extra == "test"
Requires-Dist: pyright==1.1.402; extra == "test"
Requires-Dist: pytest==8.4.1; extra == "test"
Requires-Dist: pytest-cov==6.2.1; extra == "test"
Requires-Dist: pytest-xdist==3.7.0; extra == "test"
Dynamic: license-file
